config/__init__.py
config/endpoints.py
helius/__init__.py
helius/balances.py
helius/name.py
helius/nft.py
helius/transactions.py
helius/webhooks.py
helpers/__init__.py
helpers/utility.py
helius-0.0.2.dist-info/LICENSE
helius-0.0.2.dist-info/METADATA
helius-0.0.2.dist-info/WHEEL
helius-0.0.2.dist-info/top_level.txt
helius-0.0.2.dist-info/RECORD
