Metadata-Version: 2.1
Name: helius
Version: 0.0.2
Summary: Python SDK for interacting with the Official Helius APIs - https://docs.helius.xyz/api-reference/
Home-page: https://github.com/vmpyre/helius_sdk
Author: vmpyre.sol#0001 (Discord)
Author-email: vmpyrestax@gmail.com
Project-URL: Bug Tracker, https://github.com/vmpyre/helius_sdk/issues
Classifier: Programming Language :: Python :: 3
Classifier: License :: OSI Approved :: MIT License
Classifier: Operating System :: OS Independent
Requires-Python: >=3.8
License-File: LICENSE
